{"name":"region","identifier":"RQSAIQX6N3","description":null,"slotTypeName":"region","obfuscationSetting":null,"valueElicitationSetting":{"promptSpecification":{"allowInterrupt":true,"messageGroupsList":[{"message":{"ssmlMessage":null,"customPayload":null,"plainTextMessage":{"value":"what AWS region would you like to use?"},"imageResponseCard":null},"variations":null}],"maxRetries":4},"slotConstraint":"Required","defaultValueSpecification":null,"sampleUtterances":null,"waitAndContinueSpecification":null},"multipleValuesSetting":null}