{"name":"s3-create-bucket","identifier":"2ZLEKBMWTO","description":null,"parentIntentSignature":null,"sampleUtterances":[{"utterance":"Create a bucket named {bucketName}  "},{"utterance":"Create a bucket with the following name: {bucketName}  "},{"utterance":"Create an S3 bucket named {bucketName}  "},{"utterance":"Create an S3 bucket"},{"utterance":"Create a new S3 bucket named {bucketName}"}],"intentConfirmationSetting":null,"intentClosingSetting":null,"inputContexts":null,"outputContexts":[{"name":"s3-bucket-created","timeToLiveInSeconds":3600,"turnsToLive":5}],"kendraConfiguration":null,"dialogCodeHook":null,"fulfillmentCodeHook":{"postFulfillmentStatusSpecification":null,"fulfillmentUpdatesSpecification":null,"enabled":true},"slotPriorities":[{"priority":1,"slotName":"bucketName"}]}